{
  "project_info": {
    "project_number": "209196809810",
    "project_id": "pillionpal-25a60",
    "storage_bucket": "pillionpal-25a60.firebasestorage.app"
  },
  "client": [
    {
      "client_info": {
        "mobilesdk_app_id": "1:209196809810:android:9ed3eb8d4af62715c0a98b",
        "android_client_info": {
          "package_name": "com.example.my_flutter_app"
        }
      },
      "oauth_client": [
        {
          "client_id": "209196809810-mkrioenoqgj9qfad7pp9puv1oq4ata4c.apps.googleusercontent.com",
          "client_type": 3
        }
      ],
      "api_key": [
        {
          "current_key": "AIzaSyCABMb7JwE-AQprufUma2KdU-qMALKUfZA"
        }
      ],
      "services": {
        "appinvite_service": {
          "other_platform_oauth_client": [
            {
              "client_id": "209196809810-mkrioenoqgj9qfad7pp9puv1oq4ata4c.apps.googleusercontent.com",
              "client_type": 3
            },
            {
              "client_id": "209196809810-d5frai4ogo5bnarfs9mlhmuo2igof98q.apps.googleusercontent.com",
              "client_type": 2,
              "ios_info": {
                "bundle_id": "com.example.myFlutterApp"
              }
            }
          ]
        }
      }
    }
  ],
  "configuration_version": "1"
}